hawkeye/__init__.py
hawkeye/demo.py
hawkeye/face/__init__.py
hawkeye/face/src/__init__.py
hawkeye/face/src/aux_functions.py
hawkeye/face/src/face_align.py
hawkeye/face/src/face_detection.py
hawkeye/face/src/face_embedding.py
hawkeye/face/src/landmark.py
hawkeye/face/src/reference_world.py
hawkeye/ocr/__init__.py
hawkeye/tracking/__init__.py
hawkeye/tracking/src/__init__.py
hawkeye/tracking/src/basetrack.py
hawkeye/tracking/src/byte_tracker.py
hawkeye/tracking/src/kalman_filter.py
hawkeye/tracking/src/matching.py
hawkeye_v2-1.0.5.dist-info/LICENSE
hawkeye_v2-1.0.5.dist-info/METADATA
hawkeye_v2-1.0.5.dist-info/WHEEL
hawkeye_v2-1.0.5.dist-info/top_level.txt
hawkeye_v2-1.0.5.dist-info/RECORD
