Metadata-Version: 2.1
Name: hawkeye-v2
Version: 1.0.5
Summary: Face recognize, Object tracking, OCR
Home-page: https://github.com/Duy-NM/hawk_eye
Author: Duy Nguyen Manh
Author-email: manhduy160396@email.com
License: MIT License
License-File: LICENSE
Requires-Dist: opencv-python
Requires-Dist: gdown
Requires-Dist: onnx
Requires-Dist: onnxruntime-gpu (==1.7)
